pgvecto_rs-0.2.2.dist-info/METADATA
pgvecto_rs-0.2.2.dist-info/WHEEL
pgvecto_rs-0.2.2.dist-info/entry_points.txt
pgvecto_rs-0.2.2.dist-info/licenses/LICENSE
pgvecto_rs/__init__.py
pgvecto_rs/django/__init__.py
pgvecto_rs/django/bvector.py
pgvecto_rs/django/extensions.py
pgvecto_rs/django/functions.py
pgvecto_rs/django/indexes.py
pgvecto_rs/django/svector.py
pgvecto_rs/django/vecf16.py
pgvecto_rs/django/vector.py
pgvecto_rs/errors.py
pgvecto_rs/psycopg/__init__.py
pgvecto_rs/psycopg/bvector.py
pgvecto_rs/psycopg/register.py
pgvecto_rs/psycopg/svector.py
pgvecto_rs/psycopg/vecf16.py
pgvecto_rs/psycopg/vector.py
pgvecto_rs/sdk/__init__.py
pgvecto_rs/sdk/client.py
pgvecto_rs/sdk/filters.py
pgvecto_rs/sdk/record.py
pgvecto_rs/sqlalchemy/__init__.py
pgvecto_rs/sqlalchemy/bvector.py
pgvecto_rs/sqlalchemy/svector.py
pgvecto_rs/sqlalchemy/vecf16.py
pgvecto_rs/sqlalchemy/vector.py
pgvecto_rs/types/__init__.py
pgvecto_rs/types/bvector.py
pgvecto_rs/types/index.py
pgvecto_rs/types/svector.py
pgvecto_rs/types/vecf16.py
pgvecto_rs/types/vector.py
pgvecto_rs-0.2.2.dist-info/RECORD
