Metadata-Version: 2.1
Name: pgvecto-rs
Version: 0.2.2
Summary: Python binding for pgvecto.rs
Author-Email: TensorChord <envd-maintainers@tensorchord.ai>, =?utf-8?b?55uQ57KSIFlhbmxp?= <mail@yanli.one>, cutecutecat <junyuchen@tensorchord.ai>
License: Apache-2.0
Classifier: Programming Language :: Python :: 3 :: Only
Classifier: Programming Language :: Python :: 3.8
Classifier: Programming Language :: Python :: 3.9
Classifier: Programming Language :: Python :: 3.10
Classifier: Programming Language :: Python :: 3.11
Classifier: Programming Language :: Python :: 3.12
Requires-Python: <3.13,>=3.8
Requires-Dist: numpy>=1.23
Requires-Dist: toml>=0.10
Provides-Extra: psycopg3
Requires-Dist: psycopg[binary]>=3.1.12; extra == "psycopg3"
Provides-Extra: sdk
Requires-Dist: openai>=1.2.2; extra == "sdk"
Requires-Dist: pgvecto_rs[sqlalchemy]; extra == "sdk"
Provides-Extra: sqlalchemy
Requires-Dist: SQLAlchemy>=2.0.23; extra == "sqlalchemy"
Provides-Extra: django
Requires-Dist: Django>=4.2; extra == "django"
